g42cloudsdkevs/__init__.py
g42cloudsdkevs/v2/__init__.py
g42cloudsdkevs/v2/evs_async_client.py
g42cloudsdkevs/v2/evs_client.py
g42cloudsdkevs/v2/model/__init__.py
g42cloudsdkevs/v2/model/attachment.py
g42cloudsdkevs/v2/model/az_info.py
g42cloudsdkevs/v2/model/batch_create_volume_tags_request.py
g42cloudsdkevs/v2/model/batch_create_volume_tags_request_body.py
g42cloudsdkevs/v2/model/batch_create_volume_tags_response.py
g42cloudsdkevs/v2/model/batch_delete_volume_tags_request.py
g42cloudsdkevs/v2/model/batch_delete_volume_tags_request_body.py
g42cloudsdkevs/v2/model/batch_delete_volume_tags_response.py
g42cloudsdkevs/v2/model/bss_param_for_create_volume.py
g42cloudsdkevs/v2/model/bss_param_for_resize_volume.py
g42cloudsdkevs/v2/model/cinder_accept_volume_transfer_option.py
g42cloudsdkevs/v2/model/cinder_accept_volume_transfer_request.py
g42cloudsdkevs/v2/model/cinder_accept_volume_transfer_request_body.py
g42cloudsdkevs/v2/model/cinder_accept_volume_transfer_response.py
g42cloudsdkevs/v2/model/cinder_create_volume_transfer_request.py
g42cloudsdkevs/v2/model/cinder_create_volume_transfer_request_body.py
g42cloudsdkevs/v2/model/cinder_create_volume_transfer_response.py
g42cloudsdkevs/v2/model/cinder_delete_volume_transfer_request.py
g42cloudsdkevs/v2/model/cinder_delete_volume_transfer_response.py
g42cloudsdkevs/v2/model/cinder_list_availability_zones_request.py
g42cloudsdkevs/v2/model/cinder_list_availability_zones_response.py
g42cloudsdkevs/v2/model/cinder_list_quotas_request.py
g42cloudsdkevs/v2/model/cinder_list_quotas_response.py
g42cloudsdkevs/v2/model/cinder_list_volume_transfers_request.py
g42cloudsdkevs/v2/model/cinder_list_volume_transfers_response.py
g42cloudsdkevs/v2/model/cinder_list_volume_types_request.py
g42cloudsdkevs/v2/model/cinder_list_volume_types_response.py
g42cloudsdkevs/v2/model/cinder_show_volume_transfer_request.py
g42cloudsdkevs/v2/model/cinder_show_volume_transfer_response.py
g42cloudsdkevs/v2/model/create_snapshot_option.py
g42cloudsdkevs-0.0.10b0.dist-info/LICENSE
g42cloudsdkevs-0.0.10b0.dist-info/METADATA
g42cloudsdkevs-0.0.10b0.dist-info/WHEEL
g42cloudsdkevs-0.0.10b0.dist-info/top_level.txt
g42cloudsdkevs-0.0.10b0.dist-info/RECORD
