Metadata-Version: 2.1
Name: g42cloudsdkevs
Version: 0.0.10b0
Summary: EVS
Home-page: https://github.com/g42cloud-sdk/g42cloud-sdk-python
Author: G42Cloud SDK
Author-email: unionsdk@outlook.com
License: Apache LICENSE 2.0
Keywords: g42cloud,sdk,EVS
Classifier: Development Status :: 5 - Production/Stable
Classifier: Intended Audience :: Developers
Classifier: License :: OSI Approved :: Apache Software License
Classifier: Programming Language :: Python :: 2.7
Classifier: Programming Language :: Python :: 3.3
Classifier: Programming Language :: Python :: 3.4
Classifier: Programming Language :: Python :: 3.5
Classifier: Programming Language :: Python :: 3.6
Classifier: Programming Language :: Python :: 3.7
Classifier: Programming Language :: Python :: 3.8
Classifier: Programming Language :: Python :: 3.9
Classifier: Topic :: Software Development
Requires-Python: >=2.7,!=3.0.*,!=3.1.*,!=3.2.*
License-File: LICENSE
Requires-Dist: g42cloudsdkcore >=0.0.10-beta
